uois_datasets-0.1.0.dist-info/licenses/LICENSE
utils/__init__.py
utils/augmentation.py
utils/blob.py
utils/mask.py
uois_datasets-0.1.0.dist-info/METADATA
uois_datasets-0.1.0.dist-info/WHEEL
uois_datasets-0.1.0.dist-info/top_level.txt
uois_datasets-0.1.0.dist-info/RECORD
