Metadata-Version: 2.4
Name: uois_datasets
Version: 0.1.0
Home-page: https://github.com/jishnujayakumar/uois_datasets
Author: Jishnu Jaykumar Padalunkal
Author-email: jishnu.p@utdallas.edu
Requires-Python: >=3.7
License-File: LICENSE
Requires-Dist: torch>=1.9.0
Requires-Dist: torchvision>=0.10.0
Requires-Dist: opencv-python>=4.5.0
Requires-Dist: numpy>=1.19.0
Requires-Dist: scipy>=1.5.0
Requires-Dist: pycocotools>=2.0.2
Requires-Dist: detectron2>=0.6
Dynamic: author
Dynamic: author-email
Dynamic: home-page
Dynamic: license-file
Dynamic: requires-python
